pythonautoloader/__init__.py
pythonautoloader/mainfile.py
pythonautoloader-0.0.1.dist-info/METADATA
pythonautoloader-0.0.1.dist-info/WHEEL
pythonautoloader-0.0.1.dist-info/top_level.txt
pythonautoloader-0.0.1.dist-info/RECORD
