Metadata-Version: 2.1
Name: pythonautoloader
Version: 0.0.1
Summary: A simple auto python setup from command line
Home-page: UNKNOWN
Author: Landen Fisher
Author-email: landen6002@hotmail.com
License: UNKNOWN
Keywords: python,first package
Platform: UNKNOWN
Classifier: Development Status :: 3 - Alpha
Classifier: Intended Audience :: Education
Classifier: Programming Language :: Python :: 2
Classifier: Programming Language :: Python :: 3
Classifier: Operating System :: MacOS :: MacOS X
Classifier: Operating System :: Microsoft :: Windows
